libnano/__init__.py
libnano/barcode_tools.py
libnano/dseq.py
libnano/dseq2.cp36-win_amd64.pyd
libnano/ensemblrest.py
libnano/list_bisect.pxd
libnano/padlock.py
libnano/prostr.py
libnano/seqgraph.cp36-win_amd64.pyd
libnano/seqgraph.pyx
libnano/seqint.cp36-win_amd64.pyd
libnano/seqint.pxd
libnano/seqint.pyx
libnano/seqstr.cp36-win_amd64.pyd
libnano/seqstr.pxd
libnano/seqstr.pyx
libnano/simplethermo.cp36-win_amd64.pyd
libnano/simplethermo.pyx
libnano/util.py
libnano/cymem/__init__.py
libnano/cymem/cymem.cp36-win_amd64.pyd
libnano/cymem/cymem.pyx
libnano/datasets/__init__.py
libnano/datasets/build_codon_freq_dataset.py
libnano/datasets/build_enzyme_dataset.py
libnano/datasets/codon_freq_dataset.json
libnano/datasets/enzyme_dataset.json
libnano/datasets/padlock.yaml
libnano/datasets/barcode_sets/30_3hd_5mer_v00.json
libnano/datasets/barcode_sets/34_3hd_5mer_v00.json
libnano/datasets/barcode_sets/34_3hd_5mer_v01.json
libnano/datastructures/dseq2.cp36-win_amd64.pyd
libnano/datastructures/seqrecord/feature.cp36-win_amd64.pyd
libnano/datastructures/seqrecord/seqrecordbase.cp36-win_amd64.pyd
libnano/fileio/__init__.py
libnano/fileio/fasta.py
libnano/fileio/gb_reader.py
libnano/fileio/gb_reader_b.py
libnano/fileio/gb_writer.py
libnano/fileio/gb_writer_b.py
libnano/fileio/gbtofasta.py
libnano/fileio/naformat.py
libnano/fileio/util.py
libnano/fileio/xmfa.py
libnano/helpers/__init__.py
libnano/helpers/jsonbytes.py
libnano/helpers/textwrap.py
libnano/metric/__init__.py
libnano/metric/seqmetric.cp36-win_amd64.pyd
libnano/metric/seqmetric.pyx
libnano/metric/seqrepeat.cp36-win_amd64.pyd
libnano/metric/seqrepeat.pyx
libnano/metric/seqscreen.cp36-win_amd64.pyd
libnano/metric/seqscreen.pyx
libnano/scripts/__init__.py
libnano/scripts/geneprober.py
libnano/search/__init__.py
libnano/search/restriction.cp36-win_amd64.pyd
libnano/search/restriction.pyx
libnano/search/seedfinder.cp36-win_amd64.pyd
libnano/search/seedfinder.pyx
libnano-0.2.3.0.dist-info/DESCRIPTION.rst
libnano-0.2.3.0.dist-info/METADATA
libnano-0.2.3.0.dist-info/RECORD
libnano-0.2.3.0.dist-info/WHEEL
libnano-0.2.3.0.dist-info/entry_points.txt
libnano-0.2.3.0.dist-info/metadata.json
libnano-0.2.3.0.dist-info/top_level.txt
