Metadata-Version: 2.0
Name: libnano
Version: 0.2.3.0
Summary: Low-level nucleic acid sequence manipulation tools
Home-page: https://github.com/libnano/libnano
Author: Nick Conway, Ben Pruitt
Author-email: nick.conway@wyss.harvard.edu
License: GPLv2
Platform: UNKNOWN
Classifier: Development Status :: 4 - Beta
Classifier: Environment :: Console
Classifier: Intended Audience :: Science/Research
Classifier: Programming Language :: Python
Classifier: Programming Language :: Python :: 3
Classifier: Programming Language :: Python :: 3.6
Classifier: Programming Language :: Cython
Classifier: Topic :: Scientific/Engineering
Classifier: License :: OSI Approved :: GNU General Public License v2 (GPLv2)
Requires-Dist: six (>=1.11.0)
Requires-Dist: cython (>=0.28.3)
Requires-Dist: numpy (>=1.14.3)
Requires-Dist: PyYAML (>=3.12)
Requires-Dist: requests (>=2.18.4)
Requires-Dist: primer3-py (>=0.5.5)
Requires-Dist: click (>=6.7)
Requires-Dist: ssw-py (>=0.2.6)
Requires-Dist: pygments
Requires-Dist: pandas
Requires-Dist: colorama
